Metadata-Version: 2.1
Name: gnbd
Version: 0.6
Summary: Gaussian abd Binomial distributions
Home-page: UNKNOWN
Author: Mateus Furquim Dev
Author-email: mateus@mfurquim.dev
License: UNKNOWN
Platform: UNKNOWN
